backtester_machine/First-Machine.py
backtester_machine/Second-Machine.py
backtester_machine/Third-Machine..py
backtester_machine/tests/tests.py
backtester_machine-0.1.2.dist-info/LICENSE
backtester_machine-0.1.2.dist-info/METADATA
backtester_machine-0.1.2.dist-info/WHEEL
backtester_machine-0.1.2.dist-info/top_level.txt
backtester_machine-0.1.2.dist-info/RECORD
