Metadata-Version: 2.1
Name: backtester_machine
Version: 0.1.2
Summary: A foundational trading strategy framework for simulating and managing financial trades with customizable profit tracking and balance management.
Author-email: Liam Harris <liam.harris.tech@gmail.com>
Maintainer-email: Liam Harris <liam.harris.tech@gmail.com>
License: Unlicense
Project-URL: Homepage, https://github.com/techliam/backtester_machine
Project-URL: Issues, https://github.com/techliam/backtester_machine/Issues
Classifier: Programming Language :: Python :: 3
Classifier: License :: OSI Approved :: The Unlicense (Unlicense)
Classifier: Operating System :: OS Independent
Requires-Python: >=3.12
License-File: LICENSE
Requires-Dist: numpy >=1.23.5
Requires-Dist: pandas >=2.0.3
Requires-Dist: matplotlib >=3.8.0
